{
  "classes": {
    "base": [
      {
        "class": ".d-avatar",
        "applies": "N/A",
        "description": "Base avatar style."
      },
      {
        "class": ".d-avatar--icon",
        "applies": "d-avatar",
        "description": "Applies icon style."
      },
      {
        "class": ".d-avatar--initials",
        "applies": "d-avatar",
        "description": "Applies initials style."
      }
    ],
    "sizes": [
      {
        "class": ".d-avatar--sm",
        "applies": "d-avatar",
        "description": "Applies small size (24px)."
      },
      {
        "class": ".d-avatar--md",
        "applies": "d-avatar",
        "description": "Applies medium size (32px)."
      },
      {
        "class": ".d-avatar--lg",
        "applies": "d-avatar",
        "description": "Applies large size (48px)."
      }
    ],
    "colors": [
      {
        "class": ".d-avatar--blue-700",
        "applies": "d-avatar",
        "description": "Applies blue-700 color."
      },
      {
        "class": ".d-avatar--blue-600",
        "applies": "d-avatar",
        "description": "Applies blue-600 color."
      },
      {
        "class": ".d-avatar--blue-400",
        "applies": "d-avatar",
        "description": "Applies blue-400 color."
      },
      {
        "class": ".d-avatar--blue-200",
        "applies": "d-avatar",
        "description": "Applies blue-200 color."
      },
      {
        "class": ".d-avatar--purple-600",
        "applies": "d-avatar",
        "description": "Applies purple-600 color."
      },
      {
        "class": ".d-avatar--purple-400",
        "applies": "d-avatar",
        "description": "Applies purple-400 color."
      },
      {
        "class": ".d-avatar--purple-300",
        "applies": "d-avatar",
        "description": "Applies purple-300 color."
      },
      {
        "class": ".d-avatar--purple-200",
        "applies": "d-avatar",
        "description": "Applies purple-200 color."
      },
      {
        "class": ".d-avatar--teal-600",
        "applies": "d-avatar",
        "description": "Applies teal-600 color."
      },
      {
        "class": ".d-avatar--teal-500",
        "applies": "d-avatar",
        "description": "Applies teal-500 color."
      },
      {
        "class": ".d-avatar--teal-400",
        "applies": "d-avatar",
        "description": "Applies teal-400 color."
      },
      {
        "class": ".d-avatar--teal-200",
        "applies": "d-avatar",
        "description": "Applies teal-200 color."
      },
      {
        "class": ".d-avatar--pink-600",
        "applies": "d-avatar",
        "description": "Applies pink-600 color."
      },
      {
        "class": ".d-avatar--pink-500",
        "applies": "d-avatar",
        "description": "Applies pink-500 color."
      },
      {
        "class": ".d-avatar--pink-400",
        "applies": "d-avatar",
        "description": "Applies pink-400 color."
      },
      {
        "class": ".d-avatar--pink-200",
        "applies": "d-avatar",
        "description": "Applies pink-200 color."
      },
      {
        "class": ".d-avatar--yellow-600",
        "applies": "d-avatar",
        "description": "Applies yellow-600 color."
      },
      {
        "class": ".d-avatar--yellow-500",
        "applies": "d-avatar",
        "description": "Applies yellow-500 color."
      },
      {
        "class": ".d-avatar--yellow-400",
        "applies": "d-avatar",
        "description": "Applies yellow-400 color."
      },
      {
        "class": ".d-avatar--yellow-200",
        "applies": "d-avatar",
        "description": "Applies yellow-200 color."
      }
    ]
  }
}
