{
  "colors": [
    {
      "color": "purple",
      "stops": [
        {
          "stop": "100",
          "hex": "ECE1FF",
          "copy": "dark",
          "contrast": "AAA 15.58",
          "primary": "no"
        },
        {
          "stop": "200",
          "hex": "D1C0FF",
          "copy": "dark",
          "contrast": "AAA 11.79",
          "primary": "no"
        },
        {
          "stop": "300",
          "hex": "A687FF",
          "copy": "dark",
          "contrast": "AA 6.99",
          "primary": "no"
        },
        {
          "stop": "400",
          "hex": "8B65FF",
          "copy": "dark",
          "contrast": "AA 5.01",
          "primary": "no"
        },
        {
          "stop": "500",
          "hex": "6C3DFF",
          "copy": "white",
          "contrast": "AA 5.60",
          "primary": "yes"
        },
        {
          "stop": "600",
          "hex": "3A1C95",
          "copy": "white",
          "contrast": "AAA 11.79",
          "primary": "no"
        },
        {
          "stop": "700",
          "hex": "2A1173",
          "copy": "white",
          "contrast": "AAA 14.72",
          "primary": "no"
        },
        {
          "stop": "800",
          "hex": "160645",
          "copy": "white",
          "contrast": "AAA 18.32",
          "primary": "no"
        }
      ]
    },
    {
      "color": "black",
      "stops": [
        {
          "stop": "025",
          "hex": "F7F7F9",
          "copy": "dark",
          "contrast": "AAA 18.23",
          "primary": "no"
        },
        {
          "stop": "050",
          "hex": "EAE9EF",
          "copy": "dark",
          "contrast": "AAA 16.16",
          "primary": "no"
        },
        {
          "stop": "075",
          "hex": "DFDEE5",
          "copy": "dark",
          "contrast": "AAA 14.59",
          "primary": "no"
        },
        {
          "stop": "100",
          "hex": "CFCDD8",
          "copy": "dark",
          "contrast": "AAA 12.42",
          "primary": "no"
        },
        {
          "stop": "200",
          "hex": "B3B0C0",
          "copy": "dark",
          "contrast": "AAA 9.18",
          "primary": "no"
        },
        {
          "stop": "300",
          "hex": "9C99AC",
          "copy": "dark",
          "contrast": "AA 7.02",
          "primary": "no"
        },
        {
          "stop": "400",
          "hex": "7C7789",
          "copy": "dark",
          "contrast": "AA 4.49",
          "primary": "no"
        },
        {
          "stop": "500",
          "hex": "575564",
          "copy": "white",
          "contrast": "AAA 7.26",
          "primary": "no"
        },
        {
          "stop": "600",
          "hex": "444150",
          "copy": "white",
          "contrast": "AAA 9.91",
          "primary": "no"
        },
        {
          "stop": "700",
          "hex": "322D37",
          "copy": "white",
          "contrast": "AAA 13.40",
          "primary": "no"
        },
        {
          "stop": "800",
          "hex": "221F24",
          "copy": "white",
          "contrast": "AAA 16.28",
          "primary": "no"
        },
        {
          "stop": "900",
          "hex": "0D0C0F",
          "copy": "white",
          "contrast": "AAA 19.50",
          "primary": "yes"
        }
      ]
    },
    {
      "color": "orange",
      "stops": [
        {
          "stop": "100",
          "hex": "FFF035",
          "copy": "dark",
          "contrast": "AAA 17.50",
          "primary": "no"
        },
        {
          "stop": "200",
          "hex": "FFCCA7",
          "copy": "dark",
          "contrast": "AAA 13.41",
          "primary": "no"
        },
        {
          "stop": "300",
          "hex": "FFA360",
          "copy": "dark",
          "contrast": "AAA 9.90",
          "primary": "no"
        },
        {
          "stop": "400",
          "hex": "FF7F23",
          "copy": "dark",
          "contrast": "AAA 7.72",
          "primary": "yes"
        },
        {
          "stop": "500",
          "hex": "E05E00",
          "copy": "dark",
          "contrast": "AA 5.35",
          "primary": "no"
        },
        {
          "stop": "600",
          "hex": "43220A",
          "copy": "white",
          "contrast": "AAA 14.26",
          "primary": "no"
        }
      ]
    },
    {
      "color": "pink",
      "stops": [
        {
          "stop": "100",
          "hex": "FFEBEC",
          "copy": "dark",
          "contrast": "AAA 17.04",
          "primary": "no"
        },
        {
          "stop": "200",
          "hex": "FFD8DA",
          "copy": "dark",
          "contrast": "AAA 14.94",
          "primary": "no"
        },
        {
          "stop": "300",
          "hex": "FDA2A8",
          "copy": "dark",
          "contrast": "AAA 10.13",
          "primary": "no"
        },
        {
          "stop": "400",
          "hex": "FF578A",
          "copy": "dark",
          "contrast": "AA 6.48",
          "primary": "no"
        },
        {
          "stop": "500",
          "hex": "E92A7A",
          "copy": "dark",
          "contrast": "AA 4.71",
          "primary": "yes"
        },
        {
          "stop": "600",
          "hex": "A2114D",
          "copy": "white",
          "contrast": "AAA 7.71",
          "primary": "no"
        },
        {
          "stop": "700",
          "hex": "57102E",
          "copy": "white",
          "contrast": "AAA 13.82",
          "primary": "no"
        }
      ]
    },
    {
      "color": "yellow",
      "stops": [
        {
          "stop": "050",
          "hex": "FBF8F1",
          "copy": "dark",
          "contrast": "AAA 18.49",
          "primary": "no"
        },
        {
          "stop": "100",
          "hex": "FFF9E3",
          "copy": "dark",
          "contrast": "AAA 18.49",
          "primary": "no"
        },
        {
          "stop": "200",
          "hex": "FFEEB0",
          "copy": "dark",
          "contrast": "AAA 16.82",
          "primary": "no"
        },
        {
          "stop": "300",
          "hex": "FFCB59",
          "copy": "dark",
          "contrast": "AAA 14.42",
          "primary": "yes"
        },
        {
          "stop": "400",
          "hex": "FFCE1C",
          "copy": "dark",
          "contrast": "AAA 13.12",
          "primary": "no"
        },
        {
          "stop": "500",
          "hex": "FFBC0F",
          "copy": "dark",
          "contrast": "AAA 11.59",
          "primary": "no"
        },
        {
          "stop": "600",
          "hex": "3F2D00",
          "copy": "white",
          "contrast": "AAA 13.23",
          "primary": "no"
        }
      ]
    },
    {
      "color": "red",
      "stops": [
        {
          "stop": "100",
          "hex": "FFF1F1",
          "copy": "dark",
          "contrast": "AAA 17.68",
          "primary": "no"
        },
        {
          "stop": "200",
          "hex": "FFD3D3",
          "copy": "dark",
          "contrast": "AAA 14.36",
          "primary": "no"
        },
        {
          "stop": "300",
          "hex": "FFA7A7",
          "copy": "dark",
          "contrast": "AAA 10.49",
          "primary": "no"
        },
        {
          "stop": "400",
          "hex": "FA4646",
          "copy": "dark",
          "contrast": "AA 5.58",
          "primary": "yes"
        },
        {
          "stop": "500",
          "hex": "D81616",
          "copy": "white",
          "contrast": "AA 5.19",
          "primary": "no"
        },
        {
          "stop": "600",
          "hex": "930000",
          "copy": "white",
          "contrast": "AAA 9.37",
          "primary": "no"
        },
        {
          "stop": "700",
          "hex": "480000",
          "copy": "white",
          "contrast": "AAA 16.46",
          "primary": "no"
        }
      ]
    },
    {
      "color": "green",
      "stops": [
        {
          "stop": "100",
          "hex": "EBFFE2",
          "copy": "dark",
          "contrast": "AAA 18.89",
          "primary": "no"
        },
        {
          "stop": "200",
          "hex": "D1FFBC",
          "copy": "dark",
          "contrast": "AAA 17.40",
          "primary": "no"
        },
        {
          "stop": "300",
          "hex": "9CFF6D",
          "copy": "dark",
          "contrast": "AAA 15.73",
          "primary": "no"
        },
        {
          "stop": "400",
          "hex": "6BEE04",
          "copy": "dark",
          "contrast": "AAA 12.87",
          "primary": "yes"
        },
        {
          "stop": "500",
          "hex": "0C9B02",
          "copy": "dark",
          "contrast": "AA 5.29",
          "primary": "no"
        },
        {
          "stop": "600",
          "hex": "0A5B03",
          "copy": "white",
          "contrast": "AAA 8.36",
          "primary": "no"
        },
        {
          "stop": "700",
          "hex": "052F01",
          "copy": "white",
          "contrast": "AAA 14.85",
          "primary": "no"
        }
      ]
    }
  ]
}
