{
  "classes": [
    {
      "class": ".d-notification",
      "applies": "N/A",
      "description": "Parent modal container"
    },
    {
      "class": ".d-notification__dialog",
      "applies": "Child of <span class=\"code-example--inline\">.d-notification</span>",
      "description": "Base dialog container for modal content."
    },
    {
      "class": ".d-notification__header",
      "applies": "Child of <span class=\"code-example--inline\">.d-notification__dialog</span>",
      "description": "Adds proper styling for the modal's header."
    },
    {
      "class": ".d-notification__content",
      "applies": "Child of <span class=\"code-example--inline\">.d-notification__dialog</span>",
      "description": "Adds proper styling for the modal's content area."
    },
    {
      "class": ".d-notification__footer",
      "applies": "Child of <span class=\"code-example--inline\">.d-notification__dialog</span>",
      "description": "Adds proper styling for the modal's footer."
    },
    {
      "class": ".d-notification__close",
      "applies": "Child of <span class=\"code-example--inline\">.d-notification__dialog</span>",
      "description": "Adds proper styling for the modal's dismiss button."
    },
    {
      "class": ".d-notification--full",
      "applies": "<span class=\"code-example--inline\">.d-notification</span>",
      "description": "Makes <span class=\"code-example--inline\">.d-notification__dialog</span> take up as much of the screen as possible."
    },
    {
      "class": ".d-notification--danger",
      "applies": "<span class=\"code-example--inline\">.d-notification</span>",
      "description": "Adds styling for destructive actions."
    }
  ],
  "accessible": [
    {
      "item": "role=[state]",
      "applies": "<span class=\"code-example--inline\">.d-notification</span>",
      "description": "Labels the close element for assistive technologies. (<a class=\"d-link\" href=\"https://developer.mozilla.org/en-US/docs/Web/Accessibility/ARIA/ARIA_Techniques/Using_the_dialog_role\">Source</a>)"
    },
    {
      "item": "aria-hidden=[state]",
      "applies": "<span class=\"code-example--inline\">.d-notification</span>",
      "description": "Informs assistive technologies, such as screen readers, if they should ignore the element. This should not be confused with the HTML <span class=\"code-example--inline\">hidden</span> attribute which tells the browser to not display an element. (<a class=\"d-link\" href=\"https://developer.mozilla.org/en-US/docs/Web/Accessibility/ARIA\">Source</a>)"
    },
    {
      "item": " aria-label=\"Close\"",
      "applies": "<span class=\"code-example--inline\">.d-notification__close",
      "description": "Labels the close element for assistive technologies (<a class=\"d-link\" href=\"https://developer.mozilla.org/en-US/docs/Web/Accessibility/ARIA/ARIA_Techniques/Using_the_aria-label_attribute\">Source</a>)"
    }
  ]
}
